Shotokatan/__init__.py
Shotokatan/shortcut.py
Sh_tokatan-0.4.9.dist-info/LICENSE
Sh_tokatan-0.4.9.dist-info/METADATA
Sh_tokatan-0.4.9.dist-info/WHEEL
Sh_tokatan-0.4.9.dist-info/top_level.txt
Sh_tokatan-0.4.9.dist-info/RECORD
