Metadata-Version: 2.1
Name: Sh-tokatan
Version: 0.4.9
Summary: Shortcuts funcitions.
Home-page: https://github.com/lotexiu/Sh-tokatan
Author: Aleph (Lotexiu)
Author-email: alephcostamelo@gmail.com
Keywords: python,sqlite,keyboard,pixel capture,Pillow,teminal
Classifier: Development Status :: 1 - Planning
Classifier: Intended Audience :: Developers
Classifier: Programming Language :: Python :: 3
Classifier: License :: OSI Approved :: MIT License
Classifier: Operating System :: MacOS :: MacOS X
Classifier: Operating System :: Microsoft :: Windows
License-File: LICENSE
Requires-Dist: keyboard
Requires-Dist: pyautogui
Requires-Dist: pydirectinput
Requires-Dist: Pillow
Requires-Dist: mido
